{
  "$defs": {
    "ContractPayload": {
      "additionalProperties": false,
      "description": "Contract fields for identifying the instrument (mirrors ib_async.Contract).",
      "properties": {
        "symbol": {
          "type": "string"
        },
        "secType": {
          "default": "STK",
          "enum": [
            "STK",
            "OPT",
            "FUT",
            "IND",
            "FOP",
            "CASH",
            "CFD",
            "BAG",
            "WAR",
            "BOND",
            "CMDTY",
            "NEWS",
            "FUND",
            "CRYPTO",
            "EVENT"
          ],
          "type": "string"
        },
        "exchange": {
          "default": "SMART",
          "type": "string"
        },
        "currency": {
          "default": "USD",
          "type": "string"
        },
        "primaryExchange": {
          "default": "",
          "type": "string"
        }
      },
      "required": [
        "symbol"
      ],
      "title": "ContractPayload",
      "type": "object"
    },
    "OrderPayload": {
      "additionalProperties": false,
      "description": "Order fields for specifying the trade (mirrors ib_async.Order).",
      "properties": {
        "action": {
          "enum": [
            "BUY",
            "SELL"
          ],
          "type": "string"
        },
        "totalQuantity": {
          "exclusiveMinimum": 0,
          "type": "number"
        },
        "orderType": {
          "enum": [
            "MKT",
            "LMT"
          ],
          "type": "string"
        },
        "lmtPrice": {
          "anyOf": [
            {
              "type": "number"
            },
            {
              "type": "null"
            }
          ],
          "default": null
        },
        "tif": {
          "default": "DAY",
          "enum": [
            "DAY",
            "GTC",
            "IOC",
            "GTD",
            "OPG",
            "FOK",
            "DTC"
          ],
          "type": "string"
        },
        "outsideRth": {
          "default": false,
          "type": "boolean"
        }
      },
      "required": [
        "action",
        "totalQuantity",
        "orderType"
      ],
      "title": "OrderPayload",
      "type": "object"
    },
    "PlaceOrderPayload": {
      "additionalProperties": false,
      "description": "Top-level request body for POST /ibkr/order.",
      "properties": {
        "contract": {
          "$ref": "#/$defs/ContractPayload"
        },
        "order": {
          "$ref": "#/$defs/OrderPayload"
        }
      },
      "required": [
        "contract",
        "order"
      ],
      "title": "PlaceOrderPayload",
      "type": "object"
    },
    "PlaceOrderResponse": {
      "additionalProperties": false,
      "properties": {
        "status": {
          "type": "string"
        },
        "orderId": {
          "type": "integer"
        },
        "action": {
          "enum": [
            "BUY",
            "SELL"
          ],
          "type": "string"
        },
        "symbol": {
          "type": "string"
        },
        "totalQuantity": {
          "type": "number"
        },
        "orderType": {
          "enum": [
            "MKT",
            "LMT"
          ],
          "type": "string"
        },
        "lmtPrice": {
          "anyOf": [
            {
              "type": "number"
            },
            {
              "type": "null"
            }
          ],
          "default": null
        }
      },
      "required": [
        "status",
        "orderId",
        "action",
        "symbol",
        "totalQuantity",
        "orderType"
      ],
      "title": "PlaceOrderResponse",
      "type": "object"
    },
    "HealthResponse": {
      "additionalProperties": false,
      "properties": {
        "connected": {
          "type": "boolean"
        },
        "tradingMode": {
          "type": "string"
        }
      },
      "required": [
        "connected",
        "tradingMode"
      ],
      "title": "HealthResponse",
      "type": "object"
    },
    "FillDetail": {
      "additionalProperties": false,
      "description": "Single execution fill within a trade.",
      "properties": {
        "execId": {
          "type": "string"
        },
        "time": {
          "type": "string"
        },
        "exchange": {
          "type": "string"
        },
        "side": {
          "type": "string"
        },
        "shares": {
          "type": "number"
        },
        "price": {
          "type": "number"
        },
        "commission": {
          "type": "number"
        },
        "commissionCurrency": {
          "type": "string"
        },
        "realizedPNL": {
          "type": "number"
        }
      },
      "required": [
        "execId",
        "time",
        "exchange",
        "side",
        "shares",
        "price",
        "commission",
        "commissionCurrency",
        "realizedPNL"
      ],
      "title": "FillDetail",
      "type": "object"
    },
    "TradeDetail": {
      "additionalProperties": false,
      "description": "A trade with its order info, status, and fills.",
      "properties": {
        "orderId": {
          "type": "integer"
        },
        "action": {
          "type": "string"
        },
        "totalQuantity": {
          "type": "number"
        },
        "orderType": {
          "type": "string"
        },
        "lmtPrice": {
          "anyOf": [
            {
              "type": "number"
            },
            {
              "type": "null"
            }
          ],
          "default": null
        },
        "tif": {
          "enum": [
            "DAY",
            "GTC",
            "IOC",
            "GTD",
            "OPG",
            "FOK",
            "DTC"
          ],
          "type": "string"
        },
        "symbol": {
          "type": "string"
        },
        "secType": {
          "enum": [
            "STK",
            "OPT",
            "FUT",
            "IND",
            "FOP",
            "CASH",
            "CFD",
            "BAG",
            "WAR",
            "BOND",
            "CMDTY",
            "NEWS",
            "FUND",
            "CRYPTO",
            "EVENT"
          ],
          "type": "string"
        },
        "exchange": {
          "type": "string"
        },
        "currency": {
          "type": "string"
        },
        "status": {
          "type": "string"
        },
        "filled": {
          "type": "number"
        },
        "remaining": {
          "type": "number"
        },
        "avgFillPrice": {
          "type": "number"
        },
        "fills": {
          "items": {
            "$ref": "#/$defs/FillDetail"
          },
          "type": "array"
        }
      },
      "required": [
        "orderId",
        "action",
        "totalQuantity",
        "orderType",
        "tif",
        "symbol",
        "secType",
        "exchange",
        "currency",
        "status",
        "filled",
        "remaining",
        "avgFillPrice",
        "fills"
      ],
      "title": "TradeDetail",
      "type": "object"
    },
    "ListTradesResponse": {
      "additionalProperties": false,
      "properties": {
        "trades": {
          "items": {
            "$ref": "#/$defs/TradeDetail"
          },
          "type": "array"
        }
      },
      "required": [
        "trades"
      ],
      "title": "ListTradesResponse",
      "type": "object"
    }
  },
  "anyOf": [
    {
      "$ref": "#/$defs/PlaceOrderPayload"
    },
    {
      "$ref": "#/$defs/PlaceOrderResponse"
    },
    {
      "$ref": "#/$defs/HealthResponse"
    },
    {
      "$ref": "#/$defs/ListTradesResponse"
    }
  ]
}
